fimep/__init__.py
fimep/encode.py
fimep/fimep_model.keras
fimep/fimep_wrapper.py
fimep/prediction.py
fimep/preprocessing.py
fimep-0.1.3.dist-info/licenses/LICENSE
fimep-0.1.3.dist-info/METADATA
fimep-0.1.3.dist-info/WHEEL
fimep-0.1.3.dist-info/entry_points.txt
fimep-0.1.3.dist-info/top_level.txt
fimep-0.1.3.dist-info/RECORD
