Metadata-Version: 2.4
Name: fimep
Version: 0.1.3
Summary: An ensemble predictor that uses a deep neural network for effector prediction. Input is a dataframe of predictions from kingdom-specific programs.
Author-email: Love Odunlami <lovekayode1@gmail.com>
License: MIT License
Project-URL: Homepage, https://github.com/LoveBio/fimep
Project-URL: Issues, https://github.com/LoveBio/fimep/issues
Classifier: Programming Language :: Python :: 3
Classifier: License :: OSI Approved :: MIT License
Classifier: Operating System :: OS Independent
Requires-Python: >=3.11
License-File: LICENSE
Requires-Dist: numpy>=1.26.4
Requires-Dist: pandas>=2.2.3
Requires-Dist: keras>=3.6.0
Requires-Dist: tensorflow>=2.16.2
Requires-Dist: biopython>=1.85
Dynamic: license-file
